dlunch/__init__.py
dlunch/__main__.py
dlunch/auth.py
dlunch/cli.py
dlunch/cloud.py
dlunch/core.py
dlunch/gui.py
dlunch/models.py
dlunch/quotes.xlsx
dlunch/scheduled_tasks.py
dlunch/conf/__init__.py
dlunch/conf/config.yaml
dlunch/conf/auth/default.yaml
dlunch/conf/auth/development.yaml
dlunch/conf/auth/production.yaml
dlunch/conf/basic_auth/basic_auth.yaml
dlunch/conf/db/common.yaml
dlunch/conf/db/development.yaml
dlunch/conf/db/postgresql.yaml
dlunch/conf/db/production.yaml
dlunch/conf/db/sqlite.yaml
dlunch/conf/hydra/job_logging/custom.yaml
dlunch/conf/panel/default.yaml
dlunch/conf/panel/no_sched_clean.yaml
dlunch/conf/panel/quality.yaml
dlunch/conf/panel/gui/1st_of_april.yaml
dlunch/conf/panel/gui/4th_of_may.yaml
dlunch/conf/panel/gui/backup.yaml
dlunch/conf/panel/gui/default.yaml
dlunch/conf/panel/gui/easter.yaml
dlunch/conf/panel/gui/major_release.yaml
dlunch/conf/panel/gui/women_day.yaml
dlunch/conf/server/azure_oauth.yaml
dlunch/conf/server/basic_auth.yaml
dlunch/conf/server/common.yaml
dlunch/conf/server/development.yaml
dlunch/conf/server/github_oauth.yaml
dlunch/conf/server/no_auth.yaml
dlunch/conf/server/production.yaml
dlunch/static/css/app_header.css
dlunch/static/css/custom_tabulator.css
dlunch/static/css/flags.css
dlunch/static/css/labels.css
dlunch/static/css/stats_and_info.css
dlunch/static/css/stats_tabulator.css
dlunch/static/images/favicon.ico
dlunch/static/images/logo.png
dlunch/static/images/no_menu.png
dlunch/templates/error.html
dlunch/templates/login_basic.html
dlunch/templates/login_oauth.html
dlunch/templates/logout.html
dlunch-3.7.0.dist-info/licenses/LICENSE.md
dlunch-3.7.0.dist-info/METADATA
dlunch-3.7.0.dist-info/WHEEL
dlunch-3.7.0.dist-info/entry_points.txt
dlunch-3.7.0.dist-info/top_level.txt
dlunch-3.7.0.dist-info/RECORD
