Metadata-Version: 2.4
Name: dlunch
Version: 3.7.0
Summary: The ultimate web app for a well organized lunch.
Author-email: Michele Alberti <michele.alberti90@gmail.com>
License: Creative Commons Attribution-NonCommercial-ShareAlike 4.0 International
Project-URL: Homepage, https://github.com/Michele-Alberti/data-lunch
Project-URL: Issues, https://github.com/Michele-Alberti/data-lunch/issues
Keywords: python,webapp,lunch
Classifier: Programming Language :: Python :: 3
Classifier: License :: Free for non-commercial use
Classifier: Operating System :: OS Independent
Requires-Python: >=3.11
License-File: LICENSE.md
Requires-Dist: setuptools==80.9.0
Requires-Dist: click==8.2.1
Requires-Dist: cryptography==45.0.5
Requires-Dist: ipykernel==6.29.5
Requires-Dist: ipywidgets==8.1.7
Requires-Dist: openpyxl==3.1.5
Requires-Dist: pandas==2.3.0
Requires-Dist: passlib==1.7.4
Requires-Dist: tenacity==9.1.2
Requires-Dist: tqdm==4.67.1
Requires-Dist: panel==1.7.2
Requires-Dist: sqlalchemy==2.0.41
Requires-Dist: psycopg==3.2.9
Requires-Dist: hydra-core==1.3.2
Requires-Dist: google-cloud-storage==3.1.1
Requires-Dist: pytesseract==0.3.13
Provides-Extra: dev
Requires-Dist: jupyterlab==4.4.4; extra == "dev"
Provides-Extra: docs
Requires-Dist: mkdocs==1.6.1; extra == "docs"
Requires-Dist: mkdocstrings==0.29.1; extra == "docs"
Requires-Dist: mkdocstrings-python==1.16.12; extra == "docs"
Requires-Dist: mkdocs-material==9.6.14; extra == "docs"
Requires-Dist: mkdocs-gen-files==0.5.0; extra == "docs"
Requires-Dist: mkdocs-literate-nav==0.6.2; extra == "docs"
Requires-Dist: mkdocs-section-index==0.3.10; extra == "docs"
Requires-Dist: mkdocs-github-admonitions-plugin==0.1.1; extra == "docs"
Requires-Dist: mike==2.1.3; extra == "docs"
Requires-Dist: black==25.1.0; extra == "docs"
Dynamic: license-file
